setup.py
nada/__init__.py
nada/api.py
nada/common.py
nada/database.py
nada/downloader.py
nada/menu.py
nada/player.py
nada/singleton.py
nada/ui.py
nada.egg-info/PKG-INFO
nada.egg-info/SOURCES.txt
nada.egg-info/dependency_links.txt
nada.egg-info/entry_points.txt
nada.egg-info/not-zip-safe
nada.egg-info/requires.txt
nada.egg-info/top_level.txt