Metadata-Version: 1.0
Name: nada
Version: 0.1.3.1
Summary: Multi music website command line player
Home-page: https://github.com/ahonn/Nada
Author: ahonn
Author-email: ahonn95@outlook.com
License: MIT License
Keywords: music,luoo,cli,player
Platform: UNKNOWN
